video_danmaku/__init__.py
video_danmaku/command.py
video_danmaku/core.py
video_danmaku-0.1.1.dist-info/entry_points.txt
video_danmaku-0.1.1.dist-info/LICENSE
video_danmaku-0.1.1.dist-info/METADATA
video_danmaku-0.1.1.dist-info/WHEEL
video_danmaku-0.1.1.dist-info/RECORD
