Metadata-Version: 2.1
Name: video_danmaku
Version: 0.1.1
Summary: A simple video danmaku processing tool that supports overlaying danmaku files onto videos.
Author: 'fkl'
Author-email: 18654198191@163.com
Requires-Python: >=3.10
Classifier: Programming Language :: Python :: 3
Classifier: Programming Language :: Python :: 3.10
Classifier: Programming Language :: Python :: 3.11
Classifier: Programming Language :: Python :: 3.12
Classifier: Programming Language :: Python :: 3.13
Requires-Dist: opencv-python (>=4.10.0.84)
Requires-Dist: typer (>=0.13.0)
